{"2024-03-25T00:00:00.000":{"('Close', 'AUDUSD=X')":0.6517999768,"('High', 'AUDUSD=X')":0.6517999768,"('Low', 'AUDUSD=X')":0.6517999768,"('Open', 'AUDUSD=X')":0.6517999768,"('Volume', 'AUDUSD=X')":0},"2024-04-01T00:00:00.000":{"('Close', 'AUDUSD=X')":0.6587702036,"('High', 'AUDUSD=X')":0.6619009972,"('Low', 'AUDUSD=X')":0.6481099725,"('Open', 'AUDUSD=X')":0.6533001661,"('Volume', 'AUDUSD=X')":0},"2024-04-08T00:00:00.000":{"('Close', 'AUDUSD=X')":0.6540607214,"('High', 'AUDUSD=X')":0.6643701792,"('Low', 'AUDUSD=X')":0.6456398964,"('Open', 'AUDUSD=X')":0.6570215821,"('Volume', 'AUDUSD=X')":0},"2024-04-15T00:00:00.000":{"('Close', 'AUDUSD=X')":0.6424699426,"('High', 'AUDUSD=X')":0.6495193243,"('Low', 'AUDUSD=X')":0.6365599632,"('Open', 'AUDUSD=X')":0.6475803256,"('Volume', 'AUDUSD=X')":0},"2024-04-22T00:00:00.000":{"('Close', 'AUDUSD=X')":0.6531998515,"('High', 'AUDUSD=X')":0.6554798484,"('Low', 'AUDUSD=X')":0.6425099969,"('Open', 'AUDUSD=X')":0.6425620317,"('Volume', 'AUDUSD=X')":0},"2024-04-29T00:00:00.000":{"('Close', 'AUDUSD=X')":0.6603999138,"('High', 'AUDUSD=X')":0.6650899649,"('Low', 'AUDUSD=X')":0.6466398239,"('Open', 'AUDUSD=X')":0.6541398764,"('Volume', 'AUDUSD=X')":0},"2024-05-06T00:00:00.000":{"('Close', 'AUDUSD=X')":0.6624999642,"('High', 'AUDUSD=X')":0.6641998291,"('Low', 'AUDUSD=X')":0.655859828,"('Open', 'AUDUSD=X')":0.6609079838,"('Volume', 'AUDUSD=X')":0},"2024-05-13T00:00:00.000":{"('Close', 'AUDUSD=X')":0.6705999374,"('High', 'AUDUSD=X')":0.6714699268,"('Low', 'AUDUSD=X')":0.6586300731,"('Open', 'AUDUSD=X')":0.6601008773,"('Volume', 'AUDUSD=X')":0},"2024-05-20T00:00:00.000":{"('Close', 'AUDUSD=X')":0.6634001136,"('High', 'AUDUSD=X')":0.6710959077,"('Low', 'AUDUSD=X')":0.659320116,"('Open', 'AUDUSD=X')":0.6700705886,"('Volume', 'AUDUSD=X')":0},"2024-05-27T00:00:00.000":{"('Close', 'AUDUSD=X')":0.6665000319,"('High', 'AUDUSD=X')":0.668002665,"('Low', 'AUDUSD=X')":0.6591202021,"('Open', 'AUDUSD=X')":0.6624007821,"('Volume', 'AUDUSD=X')":0},"2024-06-03T00:00:00.000":{"('Close', 'AUDUSD=X')":0.6592001319,"('High', 'AUDUSD=X')":0.6698699594,"('Low', 'AUDUSD=X')":0.6581501961,"('Open', 'AUDUSD=X')":0.6656903028,"('Volume', 'AUDUSD=X')":0},"2024-06-10T00:00:00.000":{"('Close', 'AUDUSD=X')":0.6612999439,"('High', 'AUDUSD=X')":0.6701999307,"('Low', 'AUDUSD=X')":0.6576498747,"('Open', 'AUDUSD=X')":0.6582714915,"('Volume', 'AUDUSD=X')":0},"2024-06-17T00:00:00.000":{"('Close', 'AUDUSD=X')":0.6670001149,"('High', 'AUDUSD=X')":0.6683000326,"('Low', 'AUDUSD=X')":0.65857023,"('Open', 'AUDUSD=X')":0.6612882018,"('Volume', 'AUDUSD=X')":0},"2024-06-24T00:00:00.000":{"('Close', 'AUDUSD=X')":0.6688001156,"('High', 'AUDUSD=X')":0.6694999933,"('Low', 'AUDUSD=X')":0.6620898843,"('Open', 'AUDUSD=X')":0.663500011,"('Volume', 'AUDUSD=X')":0},"2024-07-01T00:00:00.000":{"('Close', 'AUDUSD=X')":0.6754999757,"('High', 'AUDUSD=X')":0.6754999757,"('Low', 'AUDUSD=X')":0.663500011,"('Open', 'AUDUSD=X')":0.6674007773,"('Volume', 'AUDUSD=X')":0},"2024-07-08T00:00:00.000":{"('Close', 'AUDUSD=X')":0.6768001914,"('High', 'AUDUSD=X')":0.6798604727,"('Low', 'AUDUSD=X')":0.6724298596,"('Open', 'AUDUSD=X')":0.674659133,"('Volume', 'AUDUSD=X')":0},"2024-07-15T00:00:00.000":{"('Close', 'AUDUSD=X')":0.6686999202,"('High', 'AUDUSD=X')":0.6791171432,"('Low', 'AUDUSD=X')":0.6684299707,"('Open', 'AUDUSD=X')":0.6771998405,"('Volume', 'AUDUSD=X')":0},"2024-07-22T00:00:00.000":{"('Close', 'AUDUSD=X')":0.6548998952,"('High', 'AUDUSD=X')":0.6696129441,"('Low', 'AUDUSD=X')":0.6520001888,"('Open', 'AUDUSD=X')":0.6696308851,"('Volume', 'AUDUSD=X')":0},"2024-07-29T00:00:00.000":{"('Close', 'AUDUSD=X')":0.6513999701,"('High', 'AUDUSD=X')":0.656987071,"('Low', 'AUDUSD=X')":0.6480301619,"('Open', 'AUDUSD=X')":0.6554999948,"('Volume', 'AUDUSD=X')":0},"2024-08-05T00:00:00.000":{"('Close', 'AUDUSD=X')":0.6573999524,"('High', 'AUDUSD=X')":0.6607201695,"('Low', 'AUDUSD=X')":0.6365493536,"('Open', 'AUDUSD=X')":0.6497219205,"('Volume', 'AUDUSD=X')":0},"2024-08-12T00:00:00.000":{"('Close', 'AUDUSD=X')":0.6671999693,"('High', 'AUDUSD=X')":0.6671999693,"('Low', 'AUDUSD=X')":0.6570215821,"('Open', 'AUDUSD=X')":0.6569784284,"('Volume', 'AUDUSD=X')":0},"2024-08-19T00:00:00.000":{"('Close', 'AUDUSD=X')":0.6795998812,"('High', 'AUDUSD=X')":0.6798997521,"('Low', 'AUDUSD=X')":0.6673295498,"('Open', 'AUDUSD=X')":0.6672983766,"('Volume', 'AUDUSD=X')":0},"2024-08-26T00:00:00.000":{"('Close', 'AUDUSD=X')":0.676600039,"('High', 'AUDUSD=X')":0.68250072,"('Low', 'AUDUSD=X')":0.6752499938,"('Open', 'AUDUSD=X')":0.6787806153,"('Volume', 'AUDUSD=X')":0},"2024-09-02T00:00:00.000":{"('Close', 'AUDUSD=X')":0.6670998335,"('High', 'AUDUSD=X')":0.6794701219,"('Low', 'AUDUSD=X')":0.6670998335,"('Open', 'AUDUSD=X')":0.6768001914,"('Volume', 'AUDUSD=X')":0},"2024-09-09T00:00:00.000":{"('Close', 'AUDUSD=X')":0.6706997752,"('High', 'AUDUSD=X')":0.6733099818,"('Low', 'AUDUSD=X')":0.662299931,"('Open', 'AUDUSD=X')":0.6670802236,"('Volume', 'AUDUSD=X')":0},"2024-09-16T00:00:00.000":{"('Close', 'AUDUSD=X')":0.6809999347,"('High', 'AUDUSD=X')":0.6840001345,"('Low', 'AUDUSD=X')":0.6706601977,"('Open', 'AUDUSD=X')":0.671379745,"('Volume', 'AUDUSD=X')":0},"2024-09-23T00:00:00.000":{"('Close', 'AUDUSD=X')":0.6892800927,"('High', 'AUDUSD=X')":0.6938999295,"('Low', 'AUDUSD=X')":0.6801698208,"('Open', 'AUDUSD=X')":0.6809993982,"('Volume', 'AUDUSD=X')":0},"2024-09-30T00:00:00.000":{"('Close', 'AUDUSD=X')":0.6797999144,"('High', 'AUDUSD=X')":0.6941099167,"('Low', 'AUDUSD=X')":0.6788400412,"('Open', 'AUDUSD=X')":0.691878736,"('Volume', 'AUDUSD=X')":0},"2024-10-07T00:00:00.000":{"('Close', 'AUDUSD=X')":0.6753001213,"('High', 'AUDUSD=X')":0.681198895,"('Low', 'AUDUSD=X')":0.6708298326,"('Open', 'AUDUSD=X')":0.6800592542,"('Volume', 'AUDUSD=X')":0},"2024-10-14T00:00:00.000":{"('Close', 'AUDUSD=X')":0.6706997752,"('High', 'AUDUSD=X')":0.6745999455,"('Low', 'AUDUSD=X')":0.6659700274,"('Open', 'AUDUSD=X')":0.6731105447,"('Volume', 'AUDUSD=X')":0},"2024-10-21T00:00:00.000":{"('Close', 'AUDUSD=X')":0.6637021303,"('High', 'AUDUSD=X')":0.6723200083,"('Low', 'AUDUSD=X')":0.6601967216,"('Open', 'AUDUSD=X')":0.671681881,"('Volume', 'AUDUSD=X')":0},"2024-10-28T00:00:00.000":{"('Close', 'AUDUSD=X')":0.6560999751,"('High', 'AUDUSD=X')":0.6611133218,"('Low', 'AUDUSD=X')":0.6537400484,"('Open', 'AUDUSD=X')":0.6603406072,"('Volume', 'AUDUSD=X')":0},"2024-11-04T00:00:00.000":{"('Close', 'AUDUSD=X')":0.6582845449,"('High', 'AUDUSD=X')":0.6687889695,"('Low', 'AUDUSD=X')":0.6515209675,"('Open', 'AUDUSD=X')":0.6591914296,"('Volume', 'AUDUSD=X')":0},"2024-11-11T00:00:00.000":{"('Close', 'AUDUSD=X')":0.6463999152,"('High', 'AUDUSD=X')":0.6597998738,"('Low', 'AUDUSD=X')":0.6444000602,"('Open', 'AUDUSD=X')":0.6584578753,"('Volume', 'AUDUSD=X')":0},"2024-11-18T00:00:00.000":{"('Close', 'AUDUSD=X')":0.6505998969,"('High', 'AUDUSD=X')":0.654600203,"('Low', 'AUDUSD=X')":0.6448500752,"('Open', 'AUDUSD=X')":0.6463413835,"('Volume', 'AUDUSD=X')":0},"2024-11-25T00:00:00.000":{"('Close', 'AUDUSD=X')":0.6520001888,"('High', 'AUDUSD=X')":0.6549302936,"('Low', 'AUDUSD=X')":0.6435200572,"('Open', 'AUDUSD=X')":0.6539880037,"('Volume', 'AUDUSD=X')":0},"2024-12-02T00:00:00.000":{"('Close', 'AUDUSD=X')":0.6392999291,"('High', 'AUDUSD=X')":0.6510882974,"('Low', 'AUDUSD=X')":0.6379601955,"('Open', 'AUDUSD=X')":0.6501992941,"('Volume', 'AUDUSD=X')":0},"2024-12-09T00:00:00.000":{"('Close', 'AUDUSD=X')":0.6360999346,"('High', 'AUDUSD=X')":0.6472001672,"('Low', 'AUDUSD=X')":0.6337798238,"('Open', 'AUDUSD=X')":0.639701128,"('Volume', 'AUDUSD=X')":0},"2024-12-16T00:00:00.000":{"('Close', 'AUDUSD=X')":0.6253998876,"('High', 'AUDUSD=X')":0.638499856,"('Low', 'AUDUSD=X')":0.6201396585,"('Open', 'AUDUSD=X')":0.6368291378,"('Volume', 'AUDUSD=X')":0},"2024-12-23T00:00:00.000":{"('Close', 'AUDUSD=X')":0.621800065,"('High', 'AUDUSD=X')":0.6647397876,"('Low', 'AUDUSD=X')":0.6201300025,"('Open', 'AUDUSD=X')":0.6254104376,"('Volume', 'AUDUSD=X')":0},"2024-12-30T00:00:00.000":{"('Close', 'AUDUSD=X')":0.6218998432,"('High', 'AUDUSD=X')":0.6246599555,"('Low', 'AUDUSD=X')":0.6182200313,"('Open', 'AUDUSD=X')":0.6224092245,"('Volume', 'AUDUSD=X')":0},"2025-01-06T00:00:00.000":{"('Close', 'AUDUSD=X')":0.614599824,"('High', 'AUDUSD=X')":0.6301597953,"('Low', 'AUDUSD=X')":0.6141698956,"('Open', 'AUDUSD=X')":0.6221188307,"('Volume', 'AUDUSD=X')":0},"2025-01-13T00:00:00.000":{"('Close', 'AUDUSD=X')":0.6193998456,"('High', 'AUDUSD=X')":0.6246498227,"('Low', 'AUDUSD=X')":0.6132298112,"('Open', 'AUDUSD=X')":0.6154186726,"('Volume', 'AUDUSD=X')":0},"2025-01-20T00:00:00.000":{"('Close', 'AUDUSD=X')":0.6316999793,"('High', 'AUDUSD=X')":0.6333001852,"('Low', 'AUDUSD=X')":0.6197199821,"('Open', 'AUDUSD=X')":0.6198282838,"('Volume', 'AUDUSD=X')":0},"2025-01-27T00:00:00.000":{"('Close', 'AUDUSD=X')":0.6238999963,"('High', 'AUDUSD=X')":0.6306999326,"('Low', 'AUDUSD=X')":0.6206014752,"('Open', 'AUDUSD=X')":0.62940979,"('Volume', 'AUDUSD=X')":0},"2025-02-03T00:00:00.000":{"('Close', 'AUDUSD=X')":0.6271998882,"('High', 'AUDUSD=X')":0.6300998926,"('Low', 'AUDUSD=X')":0.608899951,"('Open', 'AUDUSD=X')":0.6142204404,"('Volume', 'AUDUSD=X')":0},"2025-02-10T00:00:00.000":{"('Close', 'AUDUSD=X')":0.635283649,"('High', 'AUDUSD=X')":0.6367399096,"('Low', 'AUDUSD=X')":0.6236898303,"('Open', 'AUDUSD=X')":0.6258918643,"('Volume', 'AUDUSD=X')":0},"2025-02-17T00:00:00.000":{"('Close', 'AUDUSD=X')":0.6359001398,"('High', 'AUDUSD=X')":0.6407098174,"('Low', 'AUDUSD=X')":0.6329995394,"('Open', 'AUDUSD=X')":0.6356390119,"('Volume', 'AUDUSD=X')":0},"2025-02-24T00:00:00.000":{"('Close', 'AUDUSD=X')":0.6208094954,"('High', 'AUDUSD=X')":0.6391818523,"('Low', 'AUDUSD=X')":0.6193699241,"('Open', 'AUDUSD=X')":0.6369305253,"('Volume', 'AUDUSD=X')":0},"2025-03-03T00:00:00.000":{"('Close', 'AUDUSD=X')":0.6287999153,"('High', 'AUDUSD=X')":0.6360598803,"('Low', 'AUDUSD=X')":0.6188310385,"('Open', 'AUDUSD=X')":0.622018218,"('Volume', 'AUDUSD=X')":0},"2025-03-10T00:00:00.000":{"('Close', 'AUDUSD=X')":0.6331999302,"('High', 'AUDUSD=X')":0.633599937,"('Low', 'AUDUSD=X')":0.6260799766,"('Open', 'AUDUSD=X')":0.6302905083,"('Volume', 'AUDUSD=X')":0},"2025-03-17T00:00:00.000":{"('Close', 'AUDUSD=X')":0.6275100112,"('High', 'AUDUSD=X')":0.639198184,"('Low', 'AUDUSD=X')":0.6260498166,"('Open', 'AUDUSD=X')":0.6325711012,"('Volume', 'AUDUSD=X')":0},"2025-03-24T00:00:00.000":{"('Close', 'AUDUSD=X')":0.630499959,"('High', 'AUDUSD=X')":0.6331999302,"('Low', 'AUDUSD=X')":0.6272998452,"('Open', 'AUDUSD=X')":0.6288596392,"('Volume', 'AUDUSD=X')":0},"2025-03-31T00:00:00.000":{"('Close', 'AUDUSD=X')":0.6257391572,"('High', 'AUDUSD=X')":0.6301991343,"('Low', 'AUDUSD=X')":0.6255590916,"('Open', 'AUDUSD=X')":0.6289308071,"('Volume', 'AUDUSD=X')":0}}